zepl_device/__init__.py
zepl_device/device.py
zepl_device/devices/dummy.py
zepl_device/devices/mms.py
zepl_device/devices/runner.py
zepl_device/devices/webrepl.py
zepl_device/protocols/dummy.py
zepl_device/protocols/runner.py
zepl_device/protocols/webrepl.py
zepl_device-1.1.0.dist-info/LICENSE
zepl_device-1.1.0.dist-info/METADATA
zepl_device-1.1.0.dist-info/WHEEL
zepl_device-1.1.0.dist-info/top_level.txt
zepl_device-1.1.0.dist-info/RECORD
